dbt_models_explorer/__init__.py
dbt_models_explorer/__main__.py
dbt_models_explorer/loader.py
dbt_models_explorer/render.py
dbt_models_explorer-0.1.0.dist-info/LICENSE
dbt_models_explorer-0.1.0.dist-info/METADATA
dbt_models_explorer-0.1.0.dist-info/WHEEL
dbt_models_explorer-0.1.0.dist-info/entry_points.txt
dbt_models_explorer-0.1.0.dist-info/RECORD
